neurips_cellseg_gc/Dockerfile
neurips_cellseg_gc/__init__.py
neurips_cellseg_gc/model_training_3class.py
neurips_cellseg_gc/models/__init__.py
neurips_cellseg_gc/models/unetr2d.py
neurips_cellseg_gc/predict.py
neurips_cellseg_gc/predict.sh
neurips_cellseg_gc/work_dir/__init__.py
neurips_cellseg_gc/work_dir/swinunetr_3class/best_Dice_model.pth
neurips_cellseg_gc-0.1.0.dist-info/entry_points.txt
neurips_cellseg_gc-0.1.0.dist-info/LICENSE
neurips_cellseg_gc-0.1.0.dist-info/WHEEL
neurips_cellseg_gc-0.1.0.dist-info/METADATA
neurips_cellseg_gc-0.1.0.dist-info/RECORD
